{"exist":true,"idModulo":7720193522754,"idVersion":7720193522755,"nombre":"AJ2CRB02","desc":"N/A","status":0,"resumen":{"nombre":"","depCopy":0,"depModulo":0,"ejecuciones":0,"lastSesion":null,"lastCompile":null,"lineas":0,"sentencias":0,"parrafos":0,"badStmts":0,"uid":""},"attrs":{"full":false,"cics":true,"sgdb":false,"file":false,"call":false},"maxCCParr":10,"maxCC":15,"maxStmt":25,"comment":{"blancos":35,"comentarios":572,"bloques":0,"decoradores":149},"verbos":{"verbosData":71,"verbosIO":0,"verbosControl":0,"verbosFlujo":29,"verbosArit":1,"verbosLang":0,"verbosCics":6,"verbosSQL":0},"versiones":[{"id":7720193522755,"orden":1,"uid":"Javier","fecha":1496321935000}],"parrafos":null,"maxCobertura":null,"cobertura":null}